CNLTK/NER_MODEL.py
CNLTK/NER_TAGGER_MODEL.py
CNLTK/NER_test.py
CNLTK/POS_MODEL.py
CNLTK/POS_TAGGER_MODEL.py
CNLTK/POS_test.py
CNLTK/__init__.py
CNLTK/attention.py
CNLTK/ceb_corpus.py
CNLTK/ner_tags.py
CNLTK/pos_tags.py
CNLTK/vocabulary.py
CNLTK_Beta_version-1.0.1.1.dist-info/LICENCE.txt
CNLTK_Beta_version-1.0.1.1.dist-info/METADATA
CNLTK_Beta_version-1.0.1.1.dist-info/WHEEL
CNLTK_Beta_version-1.0.1.1.dist-info/top_level.txt
CNLTK_Beta_version-1.0.1.1.dist-info/RECORD
